Metadata-Version: 2.1
Name: json2python-models
Version: 0.3.1
Summary: Python models (pydantic, attrs, dataclasses or custom) generator from JSON data with typing module support
Author-email: "bogdandm (Bogdan Kalashnikov)" <bogdan.dm1995@yandex.ru>
License: MIT
Project-URL: Repository, https://github.com/bogdandm/json2python-models
Requires-Python: >=3.9
License-File: LICENSE
Requires-Dist: python-dateutil >=2.7
Requires-Dist: inflection >=0.3
Requires-Dist: unidecode >=1.0
Requires-Dist: Jinja2 >=2.10
Requires-Dist: ordered-set ==4.*
Requires-Dist: typing-extensions >=3.1
Provides-Extra: test
Requires-Dist: pytest >=4.4.0 ; extra == 'test'
Requires-Dist: pytest-xdist ; extra == 'test'
Requires-Dist: pytest-cov ; extra == 'test'
Requires-Dist: requests ; extra == 'test'
Requires-Dist: attrs ; extra == 'test'
Requires-Dist: pydantic >=1.3 ; extra == 'test'
Requires-Dist: ruamel.yaml ; extra == 'test'
Requires-Dist: coverage ; extra == 'test'
